ansible_template_validator.py
ansible_template_validator-0.1.4.dist-info/LICENSE
ansible_template_validator-0.1.4.dist-info/METADATA
ansible_template_validator-0.1.4.dist-info/WHEEL
ansible_template_validator-0.1.4.dist-info/entry_points.txt
ansible_template_validator-0.1.4.dist-info/top_level.txt
ansible_template_validator-0.1.4.dist-info/RECORD
